{
  "primary_research_themes": [
    "Software Testing and Quality Assurance",
    "Empirical Software Engineering",
    "Mining Software Repositories"
  ],
  "secondary_research_themes": [
    "Program Comprehension and Code Summarization",
    "Applied Machine Learning in SE",
    "Solar Energy Simulation (Recent Shift)"
  ],
  "methodological_traits": [
    "Empirical Analysis and Validation",
    "Statistical Modeling (Causal Inference, Bayesian Statistics)",
    "Deep Neural Networks Applications",
    "Crowdsourced Manual Labeling",
    "Mathematical Modeling"
  ],
  "recurring_concepts": [
    "Mutation testing and unreached mutants",
    "Test suite effectiveness and code coverage",
    "Tangled commits in bug fixing",
    "Dynamic call graphs for event-driven programs",
    "Optimal orientation of solar panels"
  ],
  "communication_indicators": [
    "Data-driven and empirical tone",
    "Quantitative reporting of results (e.g., AUC metrics, percentages)",
    "Focus on practical implications for developers",
    "Methodical and analytical"
  ],
  "researcher_summary": "Alireza Aghamohammadi is a researcher primarily rooted in empirical software engineering with a strong emphasis on software testing, mutation testing, and mining software repositories. Their methodological approach relies heavily on rigorous statistical modeling, causal inference, and empirical validation (such as crowdsourced labeling). Secondary research explores using deep learning for code comprehension. Recently, there is a distinct interdisciplinary application of their Python and mathematical modeling skills toward solar energy optimization. Their work consistently focuses on data-driven, practical outcomes to improve developer workflows and tool effectiveness."
}